edgepi/__init__.py
edgepi/adc/__init__.py
edgepi/adc/adc_commands.py
edgepi/adc/adc_constants.py
edgepi/adc/adc_conv_time.py
edgepi/adc/adc_exceptions.py
edgepi/adc/adc_multiplexers.py
edgepi/adc/adc_query_lang.py
edgepi/adc/adc_state.py
edgepi/adc/adc_status.py
edgepi/adc/adc_voltage.py
edgepi/adc/edgepi_adc.py
edgepi/calibration/__init__.py
edgepi/calibration/calibration_constants.py
edgepi/calibration/edgepi_calibration.py
edgepi/dac/__init__.py
edgepi/dac/dac_commands.py
edgepi/dac/dac_constants.py
edgepi/dac/edgepi_dac.py
edgepi/digital_input/__init__.py
edgepi/digital_input/digital_input_constants.py
edgepi/digital_input/edgepi_digital_input.py
edgepi/digital_output/__init__.py
edgepi/digital_output/digital_output_constants.py
edgepi/digital_output/edgepi_digital_output.py
edgepi/eeprom/__init__.py
edgepi/eeprom/edgepi_eeprom.py
edgepi/eeprom/edgepi_eeprom_data.py
edgepi/eeprom/eeprom_constants.py
edgepi/eeprom/protobuf_assets/__init__.py
edgepi/eeprom/protobuf_assets/eeprom_data_classes/__init__.py
edgepi/eeprom/protobuf_assets/eeprom_data_classes/eeprom_adc_module.py
edgepi/eeprom/protobuf_assets/eeprom_data_classes/eeprom_dac_module.py
edgepi/eeprom/protobuf_assets/eeprom_data_classes/eeprom_key_module.py
edgepi/eeprom/protobuf_assets/eeprom_data_classes/eeprom_rtd_module.py
edgepi/eeprom/protobuf_assets/eeprom_data_classes/eeprom_tc_module.py
edgepi/eeprom/protobuf_assets/generated_pb2/__init__.py
edgepi/eeprom/protobuf_assets/generated_pb2/adc_module_pb2.py
edgepi/eeprom/protobuf_assets/generated_pb2/calibration_parameters_pb2.py
edgepi/eeprom/protobuf_assets/generated_pb2/dac_module_pb2.py
edgepi/eeprom/protobuf_assets/generated_pb2/edgepi_module_pb2.py
edgepi/eeprom/protobuf_assets/generated_pb2/keys_pb2.py
edgepi/eeprom/protobuf_assets/generated_pb2/rtd_module_pb2.py
edgepi/eeprom/protobuf_assets/generated_pb2/tc_module_pb2.py
edgepi/eeprom/protobuf_assets/proto_files/__init__.py
edgepi/gpio/__init__.py
edgepi/gpio/edgepi_gpio.py
edgepi_python_sdk-1.2.21.dist-info/LICENSE
edgepi_python_sdk-1.2.21.dist-info/METADATA
edgepi_python_sdk-1.2.21.dist-info/WHEEL
edgepi_python_sdk-1.2.21.dist-info/top_level.txt
edgepi_python_sdk-1.2.21.dist-info/RECORD
