Metadata-Version: 2.1
Name: edgepi-python-sdk
Version: 1.2.21
Summary: EdgePi Python SDK package
Home-page: https://github.com/EdgePi-Cloud/edgepi-python-sdk
Author: S.Park
Author-email: spark@osensa.com
Project-URL: Bug Tracker, https://github.com/EdgePi-Cloud/edgepi-python-sdk/issues
Classifier: Programming Language :: Python :: 3
Classifier: License :: OSI Approved :: MIT License
Classifier: Operating System :: OS Independent
Requires-Python: >=3.6
License-File: LICENSE
Requires-Dist: python-periphery >=2.3.0
Requires-Dist: bitstring <4.2.0,>=3.1.9
Requires-Dist: protobuf >=3.20
